ngtpl
