Metadata-Version: 1.0
Name: ngtpl
Version: 0.2.1
Summary: Collect angular templates, outputs compiled html
Home-page: http://github.com/mbr/ngtpl
Author: Marc Brinkmann
Author-email: git@marcbrinkmann.de
License: MIT
Platform: UNKNOWN
